mcp/logger.py
mcp/py.typed
mcp/client/__init__.py
mcp/client/service.py
mcp/client/session.py
mcp/client/utils.py
mcp/client/auth/__init__.py
mcp/client/auth/exceptions.py
mcp/client/auth/provider.py
mcp/client/auth/utils.py
mcp/exception/__init__.py
mcp/registry/__init__.py
mcp/registry/service.py
mcp/transport/__init__.py
mcp/transport/base.py
mcp/transport/sse.py
mcp/transport/stdio.py
mcp/transport/streamable_http.py
mcp/transport/utils.py
mcp/transport/websocket.py
mcp/types/__init__.py
mcp/types/auth.py
mcp/types/capabilities.py
mcp/types/common.py
mcp/types/completion.py
mcp/types/content.py
mcp/types/elicitation.py
mcp/types/info.py
mcp/types/initialize.py
mcp/types/json_rpc.py
mcp/types/logging.py
mcp/types/notification.py
mcp/types/ping.py
mcp/types/prompts.py
mcp/types/registry.py
mcp/types/resources.py
mcp/types/roots.py
mcp/types/sampling.py
mcp/types/schemas.py
mcp/types/stdio.py
mcp/types/tasks.py
mcp/types/tools.py
modelcontextprotocol_client-0.1.3.dist-info/METADATA
modelcontextprotocol_client-0.1.3.dist-info/WHEEL
modelcontextprotocol_client-0.1.3.dist-info/licenses/LICENSE
modelcontextprotocol_client-0.1.3.dist-info/RECORD
