Metadata-Version: 2.4
Name: modelcontextprotocol-client
Version: 0.1.3
Summary: ModelContextProtocol Client
License-File: LICENSE
Requires-Python: >=3.13
Requires-Dist: httpx-sse>=0.4.3
Requires-Dist: httpx>=0.28.1
Requires-Dist: pydantic>=2.12.3
Requires-Dist: websockets>=15.0.1
